{
  "success": true,
  "data": {
    "slug": "creator-burnout-crisis",
    "topic": "Creator Burnout Crisis",
    "description": "Creator burnout has become a critical issue in 2024, with high-profile creators taking breaks and speaking openly abo...",
    "engagement_score": 0,
    "mobile_optimized": true,
    "full_description": "Creator burnout has become a critical issue in 2024, with high-profile creators taking breaks and speaking openly about mental health challenges. The constant pressure to produce content, maintain engagement, and adapt to algorithm changes is taking its toll.",
    "keywords": [],
    "related_articles": []
  },
  "error": null,
  "meta": {
    "generated_at": "2025-06-11T16:24:46.520093",
    "cache_duration": 300
  },
  "mobile_optimized": true
}